{
  "logs": [
    { "cardNumber": "13921388123", "username": "", "date": 1575388938989 },
    { "cardNumber": "13921388123", "username": "", "date": 1575388955725 },
    { "cardNumber": "24622156195", "username": "", "date": 1575388970015 },
    { "cardNumber": "24622156195", "username": "", "date": 1575388971562 },
    { "cardNumber": "13921388123", "username": "", "date": 1575388991007 },
    { "cardNumber": "13921388123", "username": "", "date": 1575388992236 },
    { "cardNumber": "13921388123", "username": "", "date": 1575388994796 },
    { "cardNumber": "13921388123", "username": "", "date": 1575388995717 },
    { "cardNumber": "13921388123", "username": "", "date": 1575388996435 },
    { "cardNumber": "13921388123", "username": "", "date": 1575388997094 },
    { "cardNumber": "24622156195", "username": "", "date": 1575389109992 },
    { "cardNumber": "24622156195", "username": "", "date": 1575389111431 },
    { "cardNumber": "24622156195", "username": "", "date": 1575389113031 },
    { "cardNumber": "24622156195", "username": "", "date": 1575389128427 },
    { "cardNumber": "24622156195", "username": "", "date": 1575389130270 },
    { "cardNumber": "24622156195", "username": "", "date": 1575389131745 },
    { "cardNumber": "24622156195", "username": "", "date": 1575389167333 },
    { "cardNumber": "24622156195", "username": "", "date": 1575389168742 },
    { "cardNumber": "24622156195", "username": "", "date": 1575389172255 },
    { "cardNumber": "24622156195", "username": "", "date": 1575389173421 },
    { "username": "", "date": 1575389176265 },
    { "cardNumber": "24622156195", "username": "", "date": 1575389184304 },
    { "cardNumber": "24622156195", "username": "", "date": 1575389185567 },
    { "cardNumber": "24622156195", "username": "", "date": 1575389255520 },
    { "cardNumber": "24622156195", "username": "", "date": 1575389257568 },
    { "cardNumber": "24622156195", "username": "", "date": 1575389280018 },
    { "cardNumber": "24622156195", "username": "", "date": 1575389282691 },
    { "cardNumber": "13921388123", "username": "", "date": 1575389290300 },
    { "cardNumber": "24622156195", "username": "", "date": 1575389292442 },
    { "cardNumber": "13921388123", "username": "", "date": 1575389293837 },
    { "cardNumber": "13921388123", "username": "", "date": 1575389312521 },
    { "cardNumber": "24622156195", "username": "", "date": 1575389314477 },
    { "cardNumber": "13921388123", "username": "", "date": 1575389315949 },
    { "cardNumber": "24622156195", "username": "", "date": 1575389317087 },
    { "cardNumber": "13921388123", "username": "", "date": 1575389318405 },
    { "cardNumber": "13921388123", "username": "", "date": 1575389318726 },
    { "cardNumber": "24622156195", "username": "", "date": 1575389319725 },
    { "cardNumber": "13921388123", "username": "", "date": 1575389321671 },
    { "cardNumber": "24622156195", "username": "", "date": 1575389322797 },
    { "cardNumber": "13921388123", "username": "", "date": 1575389324986 },
    { "cardNumber": "24622156195", "username": "", "date": 1575389551354 },
    { "cardNumber": "13921388123", "username": "", "date": 1575389553048 },
    { "cardNumber": "24622156195", "username": "", "date": 1575389554293 },
    { "cardNumber": "13921388123", "username": "", "date": 1575389555556 },
    {
      "cardNumber": "13921388123",
      "username": "Hami ÇAKIR",
      "date": 1575389678648
    },
    { "cardNumber": "24622156195", "username": "", "date": 1575389679867 },
    { "cardNumber": "24622156195", "username": "", "date": 1575389683931 },
    {
      "cardNumber": "13921388123",
      "username": "Hami ÇAKIR",
      "date": 1575389685579
    },
    {
      "cardNumber": "13921388123",
      "username": "Hami ÇAKIR",
      "date": 1575389685746
    },
    { "cardNumber": "24622156195", "username": "", "date": 1575389686831 },
    {
      "cardNumber": "13921388123",
      "username": "Hami ÇAKIR",
      "date": 1575389688067
    },
    { "cardNumber": "24622156195", "username": "", "date": 1575389853663 },
    { "cardNumber": "24622156195", "username": "", "date": 1575389854196 },
    {
      "cardNumber": "13921388123",
      "username": "Hami ÇAKIR",
      "date": 1575389910676
    },
    { "cardNumber": "24622156195", "username": "", "date": 1575389913233 },
    {
      "cardNumber": "13921388123",
      "username": "Hami ÇAKIR",
      "date": 1575389918009
    },
    { "cardNumber": "24622156195", "username": "", "date": 1575389919382 },
    {
      "cardNumber": "13921388123",
      "username": "Hami ÇAKIR",
      "date": 1575389920850
    },
    {
      "cardNumber": "13921388123",
      "username": "Hami ÇAKIR",
      "date": 1575389921014
    },
    { "cardNumber": "24622156195", "username": "", "date": 1575389921955 },
    {
      "cardNumber": "13921388123",
      "username": "Hami ÇAKIR",
      "date": 1575389923079
    },
    { "cardNumber": "24622156195", "username": "", "date": 1575389924549 },
    {
      "cardNumber": "13921388123",
      "username": "Hami ÇAKIR",
      "date": 1575389927469
    },
    {
      "cardNumber": "13921388123",
      "username": "Hami ÇAKIR",
      "date": 1575389976068
    },
    { "cardNumber": "24622156195", "username": "", "date": 1575389977165 },
    {
      "cardNumber": "13921388123",
      "username": "Hami ÇAKIR",
      "date": 1575389978772
    },
    { "cardNumber": "24622156195", "username": "", "date": 1575389980003 },
    {
      "cardNumber": "13921388123",
      "username": "Hami ÇAKIR",
      "date": 1575389981330
    },
    { "cardNumber": "24622156195", "username": "", "date": 1575389982868 },
    {
      "cardNumber": "13921388123",
      "username": "Hami ÇAKIR",
      "date": 1575389984448
    },
    { "cardNumber": "24622156195", "username": "", "date": 1575389985736 },
    {
      "cardNumber": "13921388123",
      "username": "Hami ÇAKIR",
      "date": 1575389987271
    },
    { "cardNumber": "24622156195", "username": "", "date": 1575389988705 },
    {
      "cardNumber": "13921388123",
      "username": "Hami ÇAKIR",
      "date": 1575389990303
    },
    {
      "cardNumber": "13921388123",
      "username": "Hami ÇAKIR",
      "date": 1575389996794
    },
    {
      "cardNumber": "13921388123",
      "username": "Hami ÇAKIR",
      "date": 1575389997511
    },
    {
      "cardNumber": "13921388123",
      "username": "Hami ÇAKIR",
      "date": 1575389997611
    },
    {
      "cardNumber": "13921388123",
      "username": "Hami ÇAKIR",
      "date": 1575389998335
    },
    { "cardNumber": "24622156195", "username": "", "date": 1575390000142 },
    {
      "cardNumber": "13921388123",
      "username": "Hami ÇAKIR",
      "date": 1575390001607
    },
    { "cardNumber": "24622156195", "username": "", "date": 1575390003078 },
    {
      "cardNumber": "13921388123",
      "username": "Hami ÇAKIR",
      "date": 1575390004679
    },
    { "cardNumber": "24622156195", "username": "", "date": 1575390006067 },
    {
      "cardNumber": "13921388123",
      "username": "Hami ÇAKIR",
      "date": 1575390007649
    }
  ]
}
